prevedere/__init__.py
prevedere/api.py
prevedere_api-0.5.2.dist-info/LICENSE
prevedere_api-0.5.2.dist-info/METADATA
prevedere_api-0.5.2.dist-info/WHEEL
prevedere_api-0.5.2.dist-info/top_level.txt
prevedere_api-0.5.2.dist-info/RECORD
