Metadata-Version: 2.1
Name: prevedere-api
Version: 0.5.2
Summary: API interface for Prevedere Inc. in Python 3.6+
Home-page: https://github.com/prevedere/prevedere_api
Author: Prevedere, Inc.
Author-email: support@prevedere.com
License: UNKNOWN
Platform: UNKNOWN
Classifier: Programming Language :: Python :: 3.6
Classifier: License :: Free To Use But Restricted
Classifier: Operating System :: OS Independent
Requires-Dist: requests
